mercurifi_facilitator_sdk/__init__.py
mercurifi_facilitator_sdk/facilitator.py
mercurifi_facilitator_sdk/integrations/__init__.py
mercurifi_facilitator_sdk/integrations/evm/__init__.py
mercurifi_facilitator_sdk/integrations/evm/evm.py
mercurifi_facilitator_sdk/integrations/facilitator_api.py
mercurifi_facilitator_sdk/integrations/facilitator_interface.py
mercurifi_facilitator_sdk/integrations/facilitator_registry.py
mercurifi_facilitator_sdk/integrations/solana/__init__.py
mercurifi_facilitator_sdk/integrations/solana/solana.py
mercurifi_facilitator_sdk-1.1.0.dist-info/LICENSE
mercurifi_facilitator_sdk-1.1.0.dist-info/METADATA
mercurifi_facilitator_sdk-1.1.0.dist-info/WHEEL
mercurifi_facilitator_sdk-1.1.0.dist-info/RECORD
