Metadata-Version: 2.3
Name: mercurifi_facilitator_sdk
Version: 1.1.0
Summary: Python client for X402 Facilitator API
License: MIT
Keywords: x402,payments,facilitator,web3,usdc
Author: Mercuri
Author-email: info@mercuri.finance
Requires-Python: >=3.8,<4.0
Classifier: License :: OSI Approved :: MIT License
Classifier: Programming Language :: Python :: 3
Classifier: Programming Language :: Python :: 3.8
Classifier: Programming Language :: Python :: 3.9
Classifier: Programming Language :: Python :: 3.10
Classifier: Programming Language :: Python :: 3.11
Classifier: Programming Language :: Python :: 3.12
Classifier: Programming Language :: Python :: 3.13
Requires-Dist: base58 (==2.1.1)
Requires-Dist: cachetools (==4.2.4)
Requires-Dist: construct-typing (==0.5.6)
Requires-Dist: eth-account (==0.13.7)
Requires-Dist: h11 (==0.14.0)
Requires-Dist: httpcore (==0.16.3)
Requires-Dist: httpx (==0.23.3)
Requires-Dist: pynacl (==1.6.0)
Requires-Dist: requests (==2.32.5)
Requires-Dist: rfc3986 (==1.5.0)
Requires-Dist: solana (==0.31.0)
Requires-Dist: solders (==0.19.0)
Requires-Dist: web3 (==7.14.0)
Requires-Dist: websockets (==11.0.3)
Project-URL: Documentation, https://github.com/mercuri-finance/mercuri-facilitator-sdk-py
Project-URL: Homepage, https://github.com/mercuri-finance/mercuri-facilitator-sdk-py
Project-URL: Repository, https://github.com/mercuri-finance/mercuri-facilitator-sdk-py
